snntorch/__init__.py
snntorch/_version.py
snntorch/backprop.py
snntorch/export_nir.py
snntorch/import_nir.py
snntorch/spikegen.py
snntorch/spikeplot.py
snntorch/surrogate.py
snntorch/utils.py
snntorch/_layers/__init__.py
snntorch/_layers/bntt.py
snntorch/_layers/graded_spikes.py
snntorch/_neurons/__init__.py
snntorch/_neurons/alpha.py
snntorch/_neurons/lapicque.py
snntorch/_neurons/leaky.py
snntorch/_neurons/leakykernel.py
snntorch/_neurons/leakyparallel.py
snntorch/_neurons/leakyunroll.py
snntorch/_neurons/neurons.py
snntorch/_neurons/rleaky.py
snntorch/_neurons/rsynaptic.py
snntorch/_neurons/sconv2dlstm.py
snntorch/_neurons/slstm.py
snntorch/_neurons/synaptic.py
snntorch/functional/__init__.py
snntorch/functional/acc.py
snntorch/functional/loss.py
snntorch/functional/probe.py
snntorch/functional/quant.py
snntorch/functional/reg.py
snntorch/functional/stdp_learner.py
snntorch/spikevision/__init__.py
snntorch/spikevision/_transforms.py
snntorch/spikevision/_utils.py
snntorch/spikevision/events_timeslices.py
snntorch/spikevision/neuromorphic_dataset.py
snntorch/spikevision/spikedata/__init__.py
snntorch/spikevision/spikedata/dvs_gesture.py
snntorch/spikevision/spikedata/nmnist.py
snntorch/spikevision/spikedata/shd.py
snntorch-0.9.1.dist-info/LICENSE
snntorch-0.9.1.dist-info/METADATA
snntorch-0.9.1.dist-info/WHEEL
snntorch-0.9.1.dist-info/top_level.txt
snntorch-0.9.1.dist-info/RECORD
