Metadata-Version: 2.1
Name: snntorch
Version: 0.9.1
Summary: Deep learning with spiking neural networks.
Home-page: https://github.com/jeshraghian/snntorch
Author: Jason K. Eshraghian
Author-email: jeshragh@ucsc.edu
License: MIT License
Keywords: snntorch
Classifier: Development Status :: 2 - Pre-Alpha
Classifier: Intended Audience :: Developers
Classifier: Intended Audience :: Education
Classifier: Intended Audience :: Science/Research
Classifier: License :: OSI Approved :: MIT License
Classifier: Natural Language :: English
Classifier: Topic :: Scientific/Engineering
Classifier: Topic :: Scientific/Engineering :: Mathematics
Classifier: Topic :: Scientific/Engineering :: Artificial Intelligence
Classifier: Programming Language :: Python :: 3.8
Classifier: Programming Language :: Python :: 3.9
Classifier: Programming Language :: Python :: 3.10
Classifier: Programming Language :: Python :: 3.11
Classifier: Operating System :: OS Independent
Requires-Python: >=3.8
License-File: LICENSE
Requires-Dist: torch >=1.1.0
Requires-Dist: pandas
Requires-Dist: matplotlib
Requires-Dist: numpy >=1.17
Requires-Dist: nir
Requires-Dist: nirtorch
